fiiireflyyy/__init__.py
fiiireflyyy/firefiles.py
fiiireflyyy/firelearn.py
fiiireflyyy/fireprocess.py
fiiireflyyy/flimage.py
fiiireflyyy-0.0.7.dist-info/METADATA
fiiireflyyy-0.0.7.dist-info/WHEEL
fiiireflyyy-0.0.7.dist-info/top_level.txt
fiiireflyyy-0.0.7.dist-info/RECORD
